pynamodax/__init__.py
pynamodax/attributes.py
pynamodax/constants.py
pynamodax/exceptions.py
pynamodax/indexes.py
pynamodax/models.py
pynamodax/pagination.py
pynamodax/py.typed
pynamodax/settings.py
pynamodax/signals.py
pynamodax/transactions.py
pynamodax/types.py
pynamodax/util.py
pynamodax/connection/__init__.py
pynamodax/connection/_botocore_private.py
pynamodax/connection/base.py
pynamodax/connection/dax.py
pynamodax/connection/table.py
pynamodax/encoding/__init__.py
pynamodax/encoding/decoder.py
pynamodax/encoding/encoder.py
pynamodax/encoding/primitive_attribute_decoder.py
pynamodax/encoding/primitive_attribute_encoder.py
pynamodax/expressions/__init__.py
pynamodax/expressions/condition.py
pynamodax/expressions/operand.py
pynamodax/expressions/projection.py
pynamodax/expressions/update.py
pynamodax/expressions/util.py
pynamodax-6.1.4.dist-info/LICENSE
pynamodax-6.1.4.dist-info/METADATA
pynamodax-6.1.4.dist-info/WHEEL
pynamodax-6.1.4.dist-info/top_level.txt
pynamodax-6.1.4.dist-info/RECORD
