Metadata-Version: 2.1
Name: pynamodax
Version: 6.1.4
Summary: A Pythonic Interface to DynamoDB
Home-page: http://jlafon.io/pynamodb.html
Author: Jharrod LaFon
Author-email: jlafon@eyesopen.com
License: MIT
Project-URL: Source, https://github.com/pynamodb/PynamoDB
Keywords: python dynamodb amazon dax
Classifier: Development Status :: 5 - Production/Stable
Classifier: Intended Audience :: Developers
Classifier: Programming Language :: Python
Classifier: Operating System :: OS Independent
Classifier: Programming Language :: Python :: 3.7
Classifier: Programming Language :: Python :: 3.8
Classifier: Programming Language :: Python :: 3.9
Classifier: Programming Language :: Python :: 3.10
Classifier: License :: OSI Approved :: MIT License
Requires-Python: >=3.7
License-File: LICENSE
Requires-Dist: botocore (>=1.12.54)
Requires-Dist: typing-extensions (>=3.7) ; python_version < "3.8"
Provides-Extra: dax
Requires-Dist: amazon-dax-client (<3.0.0,>=2.0.0) ; extra == 'dax'
Provides-Extra: signals
Requires-Dist: blinker (<2.0,>=1.3) ; extra == 'signals'
